setup.py
boto/__init__.py
boto/auth.py
boto/auth_handler.py
boto/connection.py
boto/exception.py
boto/handler.py
boto/https_connection.py
boto/jsonresponse.py
boto/plugin.py
boto/provider.py
boto/regioninfo.py
boto/resultset.py
boto/storage_uri.py
boto/utils.py
boto/cacerts/__init__.py
boto/cloudformation/__init__.py
boto/cloudformation/connection.py
boto/cloudformation/stack.py
boto/cloudformation/template.py
boto/cloudfront/__init__.py
boto/cloudfront/distribution.py
boto/cloudfront/exception.py
boto/cloudfront/identity.py
boto/cloudfront/invalidation.py
boto/cloudfront/logging.py
boto/cloudfront/object.py
boto/cloudfront/origin.py
boto/cloudfront/signers.py
boto/contrib/__init__.py
boto/contrib/m2helpers.py
boto/contrib/ymlmessage.py
boto/dynamodb/__init__.py
boto/dynamodb/batch.py
boto/dynamodb/exceptions.py
boto/dynamodb/item.py
boto/dynamodb/layer1.py
boto/dynamodb/layer2.py
boto/dynamodb/schema.py
boto/dynamodb/table.py
boto/ec2/__init__.py
boto/ec2/address.py
boto/ec2/blockdevicemapping.py
boto/ec2/bundleinstance.py
boto/ec2/buyreservation.py
boto/ec2/connection.py
boto/ec2/ec2object.py
boto/ec2/image.py
boto/ec2/instance.py
boto/ec2/instanceinfo.py
boto/ec2/instancestatus.py
boto/ec2/keypair.py
boto/ec2/launchspecification.py
boto/ec2/networkinterface.py
boto/ec2/placementgroup.py
boto/ec2/regioninfo.py
boto/ec2/reservedinstance.py
boto/ec2/securitygroup.py
boto/ec2/snapshot.py
boto/ec2/spotdatafeedsubscription.py
boto/ec2/spotinstancerequest.py
boto/ec2/spotpricehistory.py
boto/ec2/tag.py
boto/ec2/volume.py
boto/ec2/zone.py
boto/ec2/autoscale/__init__.py
boto/ec2/autoscale/activity.py
boto/ec2/autoscale/group.py
boto/ec2/autoscale/instance.py
boto/ec2/autoscale/launchconfig.py
boto/ec2/autoscale/policy.py
boto/ec2/autoscale/request.py
boto/ec2/autoscale/scheduled.py
boto/ec2/autoscale/tag.py
boto/ec2/cloudwatch/__init__.py
boto/ec2/cloudwatch/alarm.py
boto/ec2/cloudwatch/datapoint.py
boto/ec2/cloudwatch/dimension.py
boto/ec2/cloudwatch/listelement.py
botornado.egg-info/PKG-INFO
botornado.egg-info/SOURCES.txt
botornado.egg-info/dependency_links.txt
botornado.egg-info/pbr.json
botornado.egg-info/requires.txt
botornado.egg-info/top_level.txt
