Metadata-Version: 1.1
Name: botornado
Version: 0.0.4
Summary: boto on tornado - an asynchronous Amazon Web Service (AWS) client
Home-page: https://github.com/yyuu/botornado
Author: Yamashita, Yuu
Author-email: peek824545201@gmail.com
License: MIT
Platform: Posix; MacOS X; Windows
Classifier: Development Status :: 3 - Alpha
Classifier: Environment :: Web Environment
Classifier: Intended Audience :: Developers
Classifier: License :: OSI Approved :: MIT License
Classifier: Operating System :: OS Independent
Classifier: Topic :: Internet
